django_utils_vish/__init__.py
django_utils_vish/management/__init__.py
django_utils_vish/management/commands/__init__.py
django_utils_vish/management/commands/list_models.py
django_utils_vish-0.1.1.dist-info/LICENSE
django_utils_vish-0.1.1.dist-info/METADATA
django_utils_vish-0.1.1.dist-info/WHEEL
django_utils_vish-0.1.1.dist-info/top_level.txt
django_utils_vish-0.1.1.dist-info/RECORD
